{
  "meta": {
    "lastId": 406
  },
  "items": [
    {
      "id": 13,
      "creatorId": 4,
      "orgId": 3,
      "workDate": "2025-09-30",
      "title": "财务管理部主任填报",
      "type": "done",
      "durationMinutes": null,
      "tags": [],
      "detail": null,
      "createdAt": "2025-09-30T08:17:30.363Z",
      "updatedAt": "2025-09-30T08:17:30.363Z"
    },
    {
      "id": 397,
      "creatorId": 4,
      "createdAt": "2025-10-05T01:09:19.108Z",
      "updatedAt": "2025-10-05T01:09:19.108Z",
      "orgId": 3,
      "workDate": "2025-09-30",
      "title": "财务管理部-主任 2025-09-30 示例工作",
      "type": "done",
      "durationMinutes": 120,
      "tags": [],
      "detail": "示例工作内容：财务管理部-主任 在 2025-09-30 完成关键任务。"
    },
    {
      "id": 398,
      "creatorId": 4,
      "createdAt": "2025-10-05T01:09:19.108Z",
      "updatedAt": "2025-10-05T01:09:19.108Z",
      "orgId": 3,
      "workDate": "2025-10-01",
      "title": "财务管理部-主任 2025-10-01 示例计划",
      "type": "plan",
      "durationMinutes": null,
      "tags": [],
      "detail": "示例计划：财务管理部-主任 在 2025-10-01 的重点安排。"
    },
    {
      "id": 399,
      "creatorId": 4,
      "createdAt": "2025-10-05T01:09:19.108Z",
      "updatedAt": "2025-10-05T01:09:19.108Z",
      "orgId": 3,
      "workDate": "2025-10-01",
      "title": "财务管理部-主任 2025-10-01 示例工作",
      "type": "done",
      "durationMinutes": 120,
      "tags": [],
      "detail": "示例工作内容：财务管理部-主任 在 2025-10-01 完成关键任务。"
    },
    {
      "id": 400,
      "creatorId": 4,
      "createdAt": "2025-10-05T01:09:19.108Z",
      "updatedAt": "2025-10-05T01:09:19.108Z",
      "orgId": 3,
      "workDate": "2025-10-02",
      "title": "财务管理部-主任 2025-10-02 示例计划",
      "type": "plan",
      "durationMinutes": null,
      "tags": [],
      "detail": "示例计划：财务管理部-主任 在 2025-10-02 的重点安排。"
    },
    {
      "id": 401,
      "creatorId": 4,
      "createdAt": "2025-10-05T01:09:19.108Z",
      "updatedAt": "2025-10-05T01:09:19.108Z",
      "orgId": 3,
      "workDate": "2025-10-02",
      "title": "财务管理部-主任 2025-10-02 示例工作",
      "type": "done",
      "durationMinutes": 120,
      "tags": [],
      "detail": "示例工作内容：财务管理部-主任 在 2025-10-02 完成关键任务。"
    },
    {
      "id": 402,
      "creatorId": 4,
      "createdAt": "2025-10-05T01:09:19.108Z",
      "updatedAt": "2025-10-05T01:09:19.108Z",
      "orgId": 3,
      "workDate": "2025-10-03",
      "title": "财务管理部-主任 2025-10-03 示例计划",
      "type": "plan",
      "durationMinutes": null,
      "tags": [],
      "detail": "示例计划：财务管理部-主任 在 2025-10-03 的重点安排。"
    },
    {
      "id": 403,
      "creatorId": 4,
      "createdAt": "2025-10-05T01:09:19.108Z",
      "updatedAt": "2025-10-05T01:09:19.108Z",
      "orgId": 3,
      "workDate": "2025-10-03",
      "title": "财务管理部-主任 2025-10-03 示例工作",
      "type": "done",
      "durationMinutes": 120,
      "tags": [],
      "detail": "示例工作内容：财务管理部-主任 在 2025-10-03 完成关键任务。"
    },
    {
      "id": 404,
      "creatorId": 4,
      "createdAt": "2025-10-05T01:09:19.108Z",
      "updatedAt": "2025-10-05T01:09:19.108Z",
      "orgId": 3,
      "workDate": "2025-10-04",
      "title": "财务管理部-主任 2025-10-04 示例计划",
      "type": "plan",
      "durationMinutes": null,
      "tags": [],
      "detail": "示例计划：财务管理部-主任 在 2025-10-04 的重点安排。"
    },
    {
      "id": 405,
      "creatorId": 4,
      "createdAt": "2025-10-05T01:09:19.108Z",
      "updatedAt": "2025-10-05T01:09:19.108Z",
      "orgId": 3,
      "workDate": "2025-10-04",
      "title": "财务管理部-主任 2025-10-04 示例工作",
      "type": "done",
      "durationMinutes": 120,
      "tags": [],
      "detail": "示例工作内容：财务管理部-主任 在 2025-10-04 完成关键任务。"
    },
    {
      "id": 406,
      "creatorId": 4,
      "createdAt": "2025-10-05T01:09:19.108Z",
      "updatedAt": "2025-10-05T01:09:19.108Z",
      "orgId": 3,
      "workDate": "2025-10-05",
      "title": "财务管理部-主任 2025-10-05 示例计划",
      "type": "plan",
      "durationMinutes": null,
      "tags": [],
      "detail": "示例计划：财务管理部-主任 在 2025-10-05 的重点安排。"
    }
  ]
}
